tinynet/__init__.py
tiny_net-1.0.2.dist-info/LICENSE
tiny_net-1.0.2.dist-info/METADATA
tiny_net-1.0.2.dist-info/WHEEL
tiny_net-1.0.2.dist-info/top_level.txt
tiny_net-1.0.2.dist-info/RECORD
