Metadata-Version: 2.1
Name: tiny-net
Version: 1.0.2
Summary: This library creates shorturl
Home-page: UNKNOWN
Author: Sudhanshu Kumar
Author-email: ksudhanshu961@gmail.com
License: MIT
Platform: UNKNOWN
Classifier: License :: OSI Approved :: MIT License
Classifier: Programming Language :: Python :: 3.6
Classifier: Programming Language :: Python :: 3.7
Classifier: Programming Language :: Python :: 3.8
Classifier: Programming Language :: Python :: 3.9
Requires-Dist: urllib3
